tracardi_text_classification/plugin.py
tracardi_text_classification/model/configuration.py
tracardi_text_classification/model/ml_source_onfiguration.py
tracardi_text_classification/model/__pycache__/configuration.cpython-38.pyc
tracardi_text_classification/model/__pycache__/ml_source_onfiguration.cpython-38.pyc
tracardi_text_classification/test/manual_test.py
tracardi_text_classification-0.6.0.dist-info/LICENSE.md
tracardi_text_classification-0.6.0.dist-info/METADATA
tracardi_text_classification-0.6.0.dist-info/WHEEL
tracardi_text_classification-0.6.0.dist-info/top_level.txt
tracardi_text_classification-0.6.0.dist-info/RECORD
